python_pandas_translation/__init__.py
python_pandas_translation/pandas_column.py
python_pandas_translation/pandas_group.py
python_pandas_translation/pandas_io.py
python_pandas_translation/pandas_query.py
python_pandas_translation/pandas_rows.py
python_pandas_translation-1.0.3.dist-info/licenses/LICENSE
python_pandas_translation-1.0.3.dist-info/METADATA
python_pandas_translation-1.0.3.dist-info/WHEEL
python_pandas_translation-1.0.3.dist-info/top_level.txt
python_pandas_translation-1.0.3.dist-info/RECORD
