Metadata-Version: 2.4
Name: python-pandas-translation
Version: 1.0.3
Summary: A Pandas DataFrame translation library
Home-page: https://github.com/aviz92/python-pandas-translation
Author: Avi Zaguri
Author-email: 
Project-URL: Repository, https://github.com/aviz92/python-pandas-translation
Requires-Python: >=3.11
License-File: LICENSE
Requires-Dist: setuptools
Requires-Dist: wheel
Requires-Dist: dotenv
Requires-Dist: custom-python-logger
Requires-Dist: pytest
Requires-Dist: pandas
Requires-Dist: openpyxl
Requires-Dist: pyarrow
Dynamic: author
Dynamic: description
Dynamic: description-content-type
Dynamic: home-page
Dynamic: license-file
Dynamic: project-url
Dynamic: requires-dist
Dynamic: requires-python
Dynamic: summary
